hooks/hook-go2_webrtc_driver.py
phosphobot/__init__.py
phosphobot/_version.py
phosphobot/ai_control.py
phosphobot/app.py
phosphobot/camera.py
phosphobot/configs.py
phosphobot/control_signal.py
phosphobot/leader_follower.py
phosphobot/main.py
phosphobot/posthog.py
phosphobot/py.typed
phosphobot/recorder.py
phosphobot/rerun_visualizer.py
phosphobot/robot.py
phosphobot/sentry.py
phosphobot/supabase.py
phosphobot/teleoperation.py
phosphobot/types.py
phosphobot/utils.py
phosphobot/am/__init__.py
phosphobot/am/act.py
phosphobot/am/base.py
phosphobot/am/gr00t.py
phosphobot/am/lerobot.py
phosphobot/am/pi05.py
phosphobot/am/smolvla.py
phosphobot/chat/__init__.py
phosphobot/chat/agent.py
phosphobot/chat/app.py
phosphobot/chat/utils.py
phosphobot/endpoints/__init__.py
phosphobot/endpoints/auth.py
phosphobot/endpoints/camera.py
phosphobot/endpoints/chat.py
phosphobot/endpoints/control.py
phosphobot/endpoints/networking.py
phosphobot/endpoints/pages.py
phosphobot/endpoints/recording.py
phosphobot/endpoints/training.py
phosphobot/endpoints/update.py
phosphobot/hardware/__init__.py
phosphobot/hardware/base.py
phosphobot/hardware/go2.py
phosphobot/hardware/koch11.py
phosphobot/hardware/lekiwi.py
phosphobot/hardware/phosphobot.py
phosphobot/hardware/piper.py
phosphobot/hardware/sim.py
phosphobot/hardware/so100.py
phosphobot/hardware/urdfloader.py
phosphobot/hardware/wx250s.py
phosphobot/hardware/motors/__init__.py
phosphobot/hardware/motors/dynamixel.py
phosphobot/hardware/motors/feetech.py
phosphobot/hardware/motors/motor_utils.py
phosphobot/models/__init__.py
phosphobot/models/camera.py
phosphobot/models/dataset.py
phosphobot/models/lerobot_dataset.py
phosphobot/models/robot.py
resources/.gitignore
resources/agilex_can_activate.sh
resources/tokens.toml
resources/calibration/koch-v1.1_58CD176940_config.json
resources/calibration/so-100_12V_config.json
resources/calibration/so-100_58CD176683_config.json
resources/calibration/so-100_58FA081789_config.json
phosphobot-0.3.134.dist-info/METADATA
phosphobot-0.3.134.dist-info/WHEEL
phosphobot-0.3.134.dist-info/entry_points.txt
phosphobot-0.3.134.dist-info/top_level.txt
phosphobot-0.3.134.dist-info/RECORD
